libsh/__init__.py
libsh/format.py
libsh/logs.py
libsh/proc/__init__.py
libsh/proc/float.py
libsh/proc/logger_filter.py
libsh/py.typed
libsh-0.1.0.dist-info/WHEEL
libsh-0.1.0.dist-info/METADATA
libsh-0.1.0.dist-info/RECORD
